seminova-0.0.2.dist-info/METADATA
seminova-0.0.2.dist-info/WHEEL
seminova-0.0.2.dist-info/licenses/LICENSE-APACHE
seminova-0.0.2.dist-info/licenses/LICENSE-MIT
seminova/__init__.py
seminova/seminova.cp312-win_amd64.pyd
seminova/seminova.pyi
seminova-0.0.2.dist-info/RECORD
