Metadata-Version: 2.4
Name: seminova
Version: 0.0.2
Classifier: Programming Language :: Python
Classifier: Programming Language :: Rust
Classifier: Programming Language :: Python :: Implementation :: CPython
Classifier: Operating System :: OS Independent
License-File: LICENSE-APACHE
License-File: LICENSE-MIT
Summary: Python bindings for an experimental SuperNova IVC (Rust backend)
Author: Xylen
License: MIT
Requires-Python: >=3.8
